treetensor/__init__.py
treetensor/common/__init__.py
treetensor/common/module.py
treetensor/common/object.py
treetensor/common/proxy.py
treetensor/common/trees.py
treetensor/common/wrappers.py
treetensor/config/__init__.py
treetensor/config/meta.py
treetensor/numpy/__init__.py
treetensor/numpy/array.py
treetensor/numpy/base.py
treetensor/numpy/funcs.py
treetensor/torch/__init__.py
treetensor/torch/size.py
treetensor/torch/stream.py
treetensor/torch/tensor.py
treetensor/torch/base/__init__.py
treetensor/torch/base/reduce.py
treetensor/torch/base/torch.py
treetensor/torch/funcs/__init__.py
treetensor/torch/funcs/autograd.py
treetensor/torch/funcs/base.py
treetensor/torch/funcs/comparison.py
treetensor/torch/funcs/construct.py
treetensor/torch/funcs/math.py
treetensor/torch/funcs/matrix.py
treetensor/torch/funcs/operation.py
treetensor/torch/funcs/reduction.py
treetensor/torch/funcs/wrapper.py
treetensor/utils/__init__.py
treetensor/utils/clazz.py
treetensor/utils/doc.py
treetensor/utils/func.py
treetensor/utils/reflection.py
DI_treetensor-0.5.0.dist-info/LICENSE
DI_treetensor-0.5.0.dist-info/METADATA
DI_treetensor-0.5.0.dist-info/WHEEL
DI_treetensor-0.5.0.dist-info/top_level.txt
DI_treetensor-0.5.0.dist-info/RECORD
