Metadata-Version: 2.1
Name: DI-treetensor
Version: 0.5.0
Summary: A flexible, generalized tree-based tensor structure.
Home-page: https://github.com/opendilab/DI-treetensor
Author: HansBug, DI-engine's Contributors
Author-email: hansbug@buaa.edu.cn
License: Apache License, Version 2.0
Keywords: Tree-structured Value Management
Classifier: Development Status :: 5 - Production/Stable
Classifier: Intended Audience :: Developers
Classifier: License :: OSI Approved :: Apache Software License
Classifier: Programming Language :: Python
Classifier: Programming Language :: Python :: 3
Classifier: Programming Language :: Python :: 3.8
Classifier: Programming Language :: Python :: 3.9
Classifier: Programming Language :: Python :: 3.10
Classifier: Programming Language :: Python :: 3.11
Classifier: Programming Language :: Python :: 3.12
Classifier: Programming Language :: Python :: Implementation :: PyPy
Requires-Python: >=3.8
License-File: LICENSE
Requires-Dist: treevalue >=1.5.0
Requires-Dist: torch >=1.10.0
Requires-Dist: hbutils >=0.6.13
Requires-Dist: numpy
Provides-Extra: doc
Requires-Dist: Jinja2 ~=3.0.0 ; extra == 'doc'
Requires-Dist: sphinx ~=3.2.0 ; extra == 'doc'
Requires-Dist: sphinx-rtd-theme ~=0.4.3 ; extra == 'doc'
Requires-Dist: enum-tools ~=0.9.0 ; extra == 'doc'
Requires-Dist: sphinx-toolbox ; extra == 'doc'
Requires-Dist: plantumlcli >=0.0.2 ; extra == 'doc'
Requires-Dist: packaging ; extra == 'doc'
Requires-Dist: sphinx-multiversion ~=0.2.4 ; extra == 'doc'
Requires-Dist: where ~=1.0.2 ; extra == 'doc'
Requires-Dist: easydict <2,>=1.7 ; extra == 'doc'
Requires-Dist: potc-torch >=0.0.1 ; extra == 'doc'
Requires-Dist: potc-treevalue >=0.0.1 ; extra == 'doc'
Provides-Extra: potc
Requires-Dist: potc-treevalue >=0.0.1 ; extra == 'potc'
Requires-Dist: potc-torch >=0.0.1 ; extra == 'potc'
Provides-Extra: test
Requires-Dist: coverage >=5 ; extra == 'test'
Requires-Dist: mock >=4.0.3 ; extra == 'test'
Requires-Dist: flake8 ~=3.5 ; extra == 'test'
Requires-Dist: pytest ~=6.2.5 ; extra == 'test'
Requires-Dist: pytest-cov ~=3.0.0 ; extra == 'test'
Requires-Dist: pytest-mock ~=3.6.1 ; extra == 'test'
Requires-Dist: pytest-xdist >=1.34.0 ; extra == 'test'
Requires-Dist: pytest-rerunfailures ~=10.2 ; extra == 'test'
Requires-Dist: pytest-timeout ~=2.0.2 ; extra == 'test'
Requires-Dist: pytest-benchmark ~=3.4.0 ; extra == 'test'
Requires-Dist: easydict <2,>=1.7 ; extra == 'test'
